Workbook

Sheet Sheet1
A1: Category | B1: Budget | C1: Actual | D1: Status
A2: Airfare | B2: 600 | C2: 525 | D2: =IF(C2<B2,"Within budget","Over budget - investigate") -> Within budget
A3: Food | B3: 350 | C3: 296 | D3: =IF(C3<B3,"Within budget","Over budget - investigate") -> Within budget
A4: Entertainment | B4: 250 | C4: 1500 | D4: =IF(C4<B4,"Within budget","Over budget - investigate") -> Over budget - investigate

Sheet Sheet2
A1: Kevin's Cookie Company
A3: Store Number | B3: State | C3: Revenue | D3: Expenses | E3: Profit/Loss | F3: Year Opened | H3: Store Number
A4: 1 | B4: NJ | C4: 1018257 | D4: 493054 | E4: 525203 | F4: 39944 | H4: 1
A5: 2 | B5: NJ | C5: 931871 | D5: 1490438 | E5: -558567 | F5: 39859 | H5: 2
A6: 3 | B6: NY | C6: 1594874 | D6: 1388020 | E6: 206854 | F6: 38351 | H6: 8
A7: 4 | B7: NY | C7: 1748345 | D7: 903161 | E7: 845184 | F7: 42531 | H7: 9
A8: 5 | B8: CT | C8: 2446179 | D8: 1178022 | E8: 1268157 | F8: 42783
A9: 6 | B9: CT | C9: 2187544 | D9: 795496 | E9: 1392048 | F9: 37495
A10: 7 | B10: CT | C10: 845272 | D10: 1519869 | E10: -674597 | F10: 39132
A11: 8 | B11: NJ | C11: 926397 | D11: 1046450 | E11: -120053 | F11: 40235
A12: 9 | B12: NJ | C12: 1714539 | D12: 403308 | E12: 1311231 | F12: 38058
A13: 10 | B13: NY | C13: 2257912 | D13: 777339 | E13: 1480573 | F13: 43631
A14: 11 | B14: PA | C14: 721331 | D14: 1744825 | E14: -1023494 | F14: 43845
A15: 12 | B15: PA | C15: 1724526 | D15: 1171129 | E15: 553397 | F15: 41430
A16: 13 | B16: PA | C16: 1355304 | D16: 539211 | E16: 816093 | F16: 37456
A17: 14 | B17: DE | C17: 2161193 | D17: 1482497 | E17: 678696 | F17: 43786
A18: 15 | B18: DE | C18: 2110777 | D18: 795381 | E18: 1315396 | F18: 41176

Sheet Sales Data Analysis
A1: Name | B1: Department | C1: Sales | D1: Month | E1: Performance | G1: Name | H1: Department | J1: Name | K1: Department
A2: David | B2: Sales | C2: 2000 | D2: Mar | E2: =IF(C2>1000, "Good", "Low") -> Good | G2: David | H2: =IFERROR(VLOOKUP(G2,Table3[#All],2,FALSE), "Not found") -> Sales | J2: David | K2: =_xlfn.XLOOKUP(J2,Table3[Name],Table3[Department],"Not Found") -> Sales
A3: Mark | B3: Sales | C3: 1500 | D3: Feb | E3: =IF(C3>1000, "Good", "Low") -> Good | G3: John | H3: =IFERROR(VLOOKUP(G3,Table3[#All],2,FALSE), "Not found") -> Sales | J3: John | K3: =_xlfn.XLOOKUP(J3,Table3[Name],Table3[Department],"Not Found") -> Sales
A4: John | B4: Sales | C4: 1200 | D4: Jan | E4: =IF(C4>1000, "Good", "Low") -> Good | G4: Sara | H4: =IFERROR(VLOOKUP(G4,Table3[#All],2,FALSE), "Not found") -> IT | J4: Sara | K4: =_xlfn.XLOOKUP(J4,Table3[Name],Table3[Department],"Not Found") -> IT
A5: Sara | B5: IT | C5: 900 | D5: Feb | E5: =IF(C5>1000, "Good", "Low") -> Low
A6: Anna | B6: HR | C6: 800 | D6: Jan | E6: =IF(C6>1000, "Good", "Low") -> Low
A8: Metric | B8: Value
A9: Total Sales: | B9: =SUBTOTAL(9, (C2:C6)) -> 6400
A11: Average Sales: | B11: =SUBTOTAL(1, (C2:C6)) -> 1280

Sheet Sheet3
A1: Cookie Names | B1: Price | D1: Cookie | E1: Price
A2: Classic Chocolate Chip Cookie | B2: 2.5 | D2: Classic Chocolate Chip Cookie | E2: =VLOOKUP(D2,Table6[#All],2,FALSE) -> 2.5
A3: Double Chocolate Chunk Cookie | B3: 3 | D3: Snickerdoodle Cookie | E3: =VLOOKUP(D3,Table6[#All],2,FALSE) -> 2.25
A4: Peanut Butter Delight | B4: 2.75 | D4: Double Chocolate Chunk Cookie | E4: =VLOOKUP(D4,Table6[#All],2,FALSE) -> 3
A5: Oatmeal Raisin Cookie | B5: 2.5
A6: White Chocolate Macadamia Nut | B6: 3.25
A7: Salted Caramel Cookie | B7: 3
A8: Snickerdoodle Cookie | B8: 2.25
A9: Lemon Sugar Cookie | B9: 2.5
A10: Triple Berry Cookie | B10: 3
A11: Mocha Espresso Cookie | B11: 3.25
A12: Almond Biscotti Cookie | B12: 2.75
A13: Mint Chocolate Chip Cookie | B13: 3
A14: Red Velvet Crinkle Cookie | B14: 3.25
A15: Butterscotch Pecan Cookie | B15: 3
A16: S’mores Cookie | B16: 3.5

Sheet xlookup
A1: Client Name | B1: Order Amount ($) | D1: Client Name | E1: Order Amount ($)
A2: TechNova Solutions | B2: 592.11 | D2: TechNova Solutions | E2: =_xlfn.XLOOKUP(D2,$A$2:$A$21,$B$2:$B$21,0,0) -> 592.11
A3: GreenLeaf Organics | B3: 88.04 | D3: Summit Apparel Co. | E3: =_xlfn.XLOOKUP(D3,$A$2:$A$21,$B$2:$B$21,0,0) -> 224.24
A4: Skyline Ventures | B4: 248.45 | D4: TechNova Solutions | E4: =_xlfn.XLOOKUP(D4,$A$2:$A$21,$B$2:$B$21,0,0) -> 592.11
A5: Summit Apparel Co. | B5: 224.24 | D5: Pinnacle Marketing Group | E5: =_xlfn.XLOOKUP(D5,$A$2:$A$21,$B$2:$B$21,0,0) -> 110.6
A6: NextGen Innovations | B6: 290.83 | D6: Evergreen Landscaping | E6: =_xlfn.XLOOKUP(D6,$A$2:$A$21,$B$2:$B$21,0,0) -> 349.58
A7: BlueWave Technologies | B7: 63.12 | D7: Peak Fitness Equipment | E7: =_xlfn.XLOOKUP(D7,$A$2:$A$21,$B$2:$B$21,0,0) -> 278.65
A8: Harmony Health Products | B8: 112.93 | D8: Stellar Events Agency | E8: =_xlfn.XLOOKUP(D8,$A$2:$A$21,$B$2:$B$21,0,0) -> 266.92
A9: EcoSphere Supplies | B9: 55.16
A10: Visionary Design Studio | B10: 183.1
A11: Pinnacle Marketing Group | B11: 110.6
A12: SwiftLogistics LLC | B12: 218.79
A13: UrbanCraft Furniture | B13: 211.77
A14: Stellar Events Agency | B14: 266.92
A15: BrightPath Education | B15: 653.99
A16: Evergreen Landscaping | B16: 349.58
A17: Dynamic Power Systems | B17: 867.45
A18: Oceanic Travel Services | B18: 781.73
A19: Peak Fitness Equipment | B19: 278.65
A20: Sunrise Solar Panels | B20: 795.15
A21: Precision Print Services | B21: 738.71

Sheet order history
A1: Month | B1: TechNova Solutions | C1: Summit Apparel Co. | D1: Pinnacle Marketing Group | E1: Evergreen Landscaping | F1: Peak Fitness Equipment | G1: Stellar Events Agency
A2: Jan | B2: 642.59 | C2: 6.57 | D2: 723.85 | E2: 827.42 | F2: 248.32 | G2: 361.44
A3: Feb | B3: 872.01 | C3: 343.36 | D3: 40.02 | E3: 378.93 | F3: 368.24 | G3: 277.22
A4: Mar | B4: 61.48 | C4: 6.67 | D4: 706.96 | E4: 647.37 | F4: 288.88 | G4: 335.65
A5: Apr | B5: 242.81 | C5: 563.9 | D5: 670.21 | E5: 749.81 | F5: 582.03 | G5: 753.41
A6: May | B6: 672.26 | C6: 905.35 | D6: 945.91 | E6: 849.36 | F6: 517.78 | G6: 169.88
A7: Jun | B7: 757.34 | C7: 652.96 | D7: 392.77 | E7: 242.38 | F7: 93.07 | G7: 342.39
A8: Jul | B8: 19.27 | C8: 933.84 | D8: 544.6 | E8: 442.48 | F8: 385.44 | G8: 590.99
A9: Aug | B9: 872.25 | C9: 213.41 | D9: 943.85 | E9: 204.89 | F9: 425.96 | G9: 182.43
A10: Sep | B10: 258.31 | C10: 926.77 | D10: 893.67 | E10: 904.34 | F10: 958.47 | G10: 309.66
A11: Oct | B11: 592.43 | C11: 39.71 | D11: 870.56 | E11: 542.99 | F11: 103.05 | G11: 668.87
A12: Nov | B12: 883.66 | C12: 692.5 | D12: 337.3 | E12: 174.05 | F12: 573.37 | G12: 444.99
A13: Dec | B13: 147.08 | C13: 748.82 | D13: 468.38 | E13: 125.48 | F13: 294.66 | G13: 352.21

Sheet may order
A1: Month | B1: TechNova Solutions | C1: Summit Apparel Co. | D1: Pinnacle Marketing Group | E1: Evergreen Landscaping | F1: Peak Fitness Equipment | G1: Stellar Events Agency
A2: May | B2: =_xlfn.XLOOKUP('may order'!B1,'order history'!$B$1:$G$1,'order history'!$B$6:$G$6) -> 672.26 | C2: =_xlfn.XLOOKUP('may order'!C1,'order history'!$B$1:$G$1,'order history'!$B$6:$G$6) -> 905.35 | D2: =_xlfn.XLOOKUP('may order'!D1,'order history'!$B$1:$G$1,'order history'!$B$6:$G$6) -> 945.91 | E2: =_xlfn.XLOOKUP('may order'!E1,'order history'!$B$1:$G$1,'order history'!$B$6:$G$6) -> 849.36 | F2: =_xlfn.XLOOKUP('may order'!F1,'order history'!$B$1:$G$1,'order history'!$B$6:$G$6) -> 517.78 | G2: =_xlfn.XLOOKUP('may order'!G1,'order history'!$B$1:$G$1,'order history'!$B$6:$G$6) -> 169.88
